Workbook

Sheet Inputs
A1: Model Objective: Assess interest rate and liquidity risk under +/- 100bps shocks using a simplified asset-liability framework
A3: Units/Convention: Amounts in CAD; rates annualized; NII annualized; liquidity metrics 30-day horizon
A4: Balance Sheet | D4: Rate Assumptions | G4: Liquidity Stress Assumptions | J4: Scenario
A5: Asset | B5: Amount | D5: Items | E5: Value | G5: Items | H5: Value | J5: Items | K5: Shock
A6: Cash | B6: 2000000 | D6: Policy/Market Rate (r) | E6: 0.04 | G6: 30-day cash inflow from loan (% of notional) | H6: 0.05 | J6: Base | K6: 0
A7: Fixed-rate Bond | B7: 5000000 | D7: Loan spread | E7: 0.02 | G7: 30-day cash outflow: ST debt rollover (% of ST debt) | H7: 0.2 | J7: Up 100bps | K7: 0.01
A8: Variable-rate Loan | B8: 8000000 | D8: Short term debt spread | E8: 0.01 | G8: 30-day cash outflow: deposit/other (set to 0 for simplicity) | H8: 0 | J8: Down 100bps | K8: -0.01
A9: Liabilities | B9: Amount | D9: Long term debt fixed rate | E9: 0.05
A10: Short term debt | B10: 6000000 | D10: Bond coupon (fixed) | E10: 0.045
A11: Long term debt | B11: 4000000
A13: Notes: For simplicity, I held liquidity runoff assumptions constant across scenarios to isolate interest rate effects. In practice, liquidity and rate shocks can be linked, but I wanted to focus on core rate sensitivity.

Sheet Model
A1: Item | B1: Base | C1: +100 bps | D1: -100 bps
A2: Market rate | B2: =Inputs!$E$6+Inputs!$K$6 -> 0.04 | C2: =B2+Inputs!K7 -> 0.05 | D2: =B2+Inputs!K8 -> 0.03
A3: Loan rate | B3: =B2+Inputs!E7 -> 0.06 | C3: =C2+Inputs!E7 -> 0.07 | D3: =D2+Inputs!E7 -> 0.05
A4: ST debt rate | B4: =Model!B2+Inputs!E8 -> 0.05 | C4: =C2+Inputs!E8 -> 0.06 | D4: =D2+Inputs!E8 -> 0.04
A6: Base | F6: Up | K6: Down
A7: Asset | B7: Balance | C7: Rate (Base) | D7: Annual Interest (Base) | F7: Asset | G7: Balance | H7: Rate (Up) | I7: Annual Interest (Up) | K7: Asset | L7: Balance | M7: Rate (Down) | N7: Annual Interest (Down)
A8: Cash | B8: =Inputs!B6 -> 2000000 | C8: 0 | D8: =B8*C8 -> 0 | F8: Cash | G8: =Inputs!B6 -> 2000000 | H8: 0 | I8: =G8*H8 -> 0 | K8: Cash | L8: =Inputs!B6 -> 2000000 | M8: 0 | N8: =L8*M8 -> 0
A9: Fixed-rate Bond | B9: =Inputs!B7 -> 5000000 | C9: =Inputs!E10 -> 0.045 | D9: =B9*C9 -> 225000 | F9: Fixed-rate Bond | G9: =Inputs!B7 -> 5000000 | H9: =Inputs!E10 -> 0.045 | I9: =G9*H9 -> 225000 | K9: Fixed-rate Bond | L9: =Inputs!B7 -> 5000000 | M9: =Inputs!E10 -> 0.045 | N9: =L9*M9 -> 225000
A10: Variable-rate Loan | B10: =Inputs!B8 -> 8000000 | C10: =B3 -> 0.06 | D10: =B10*C10 -> 480000 | F10: Variable-rate Loan | G10: =Inputs!B8 -> 8000000 | H10: =C3 -> 0.07 | I10: =G10*H10 -> 560000 | K10: Variable-rate Loan | L10: =Inputs!B8 -> 8000000 | M10: =D3 -> 0.05 | N10: =L10*M10 -> 400000
A11: Liabilities | F11: Liabilities | K11: Liabilities
A12: Short term debt | B12: =Inputs!B10 -> 6000000 | C12: =B4 -> 0.05 | D12: =B12*C12 -> 300000 | F12: Short term debt | G12: =Inputs!B10 -> 6000000 | H12: =C4 -> 0.06 | I12: =G12*H12 -> 360000 | K12: Short term debt | L12: =Inputs!B10 -> 6000000 | M12: =D4 -> 0.04 | N12: =L12*M12 -> 240000
A13: Long term debt | B13: =Inputs!B11 -> 4000000 | C13: =Inputs!E9 -> 0.05 | D13: =B13*C13 -> 200000 | F13: Long term debt | G13: =Inputs!B11 -> 4000000 | H13: =Inputs!E9 -> 0.05 | I13: =G13*H13 -> 200000 | K13: Long term debt | L13: =Inputs!B11 -> 4000000 | M13: =Inputs!E9 -> 0.05 | N13: =L13*M13 -> 200000
A14: Net Interest Income (NII) | F14: Net Interest Income (NII) | K14: Net Interest Income (NII)
A15: Interest Income_base | B15: =SUM(D8:D10) -> 705000 | F15: Interest Income_base | G15: =SUM(I8:I10) -> 785000 | K15: Interest Income_down | L15: =SUM(N8:N10) -> 625000
A16: Interest Expense_base | B16: =SUM(D12:D13) -> 500000 | F16: Interest Expense_base | G16: =SUM(I12:I13) -> 560000 | K16: Interest Expense_down | L16: =SUM(N12:N13) -> 440000
A17: NII_base | B17: =B15-B16 -> 205000 | F17: NII_base | G17: =G15-G16 -> 225000 | K17: NII_down | L17: =L15-L16 -> 185000
A19: 30-day cash flow
A20: 30-day inflows
A21: Loan inflow | B21: =B10*Inputs!H6 -> 400000
A22: Bond inflow | B22: 0
A23: Total inflow | B23: =SUM(B21:B22) -> 400000
A24: 30-day outflows
A25: ST debt outflow | B25: =B12*Inputs!H7 -> 1200000
A26: other outflow | B26: 0
A27: Total outflow | B27: =SUM(B25:B26) -> 1200000
A28: Net Cash Flow
A29: Net Cash after stress | B29: =B8+B23-B27 -> 1200000
A30: Simplified LCR | B30: =(B8+B23)/B27 -> 2

Sheet Results
A1: NII under scenarios | F1: Liquidity
A2: Scenario | B2: NII | C2: ΔNII | D2: ΔNII% | F2: Scenario | G2: Cash after stress | H2: LCR
A3: Base | B3: =Model!B17 -> 205000 | C3: =B3-$B$3 -> 0 | D3: =IFERROR(B3/$B$3-1,0) -> 0 | F3: Base | G3: =Model!B29 -> 1200000 | H3: =Model!B30 -> 2
A4: Up (+100bps) | B4: =Model!G17 -> 225000 | C4: =B4-$B$3 -> 20000 | D4: =IFERROR(B4/$B$3-1,0) -> 0.097560976 | F4: Up (+100bps) | G4: =Model!B29 -> 1200000 | H4: =Model!B30 -> 2
A5: Down (-100bps) | B5: =Model!L17 -> 185000 | C5: =B5-$B$3 -> -20000 | D5: =IFERROR(B5/$B$3-1,0) -> -0.097560976 | F5: Down (-100bps) | G5: =Model!B29 -> 1200000 | H5: =Model!B30 -> 2
I7: Results:
I9: Under +/-100bps, NII increases/decreases by 20000 or 9.76% due to the re-pricing gap between variable-rate assets and short-term funding.
I11: Liquidity stress test shows 30-day cash position remains positive given assumed runoff rates.
I13: Identified key exposure drivers: proportion of variable-rate loans, short-term debt reliance, and initial cash buffer.
I15: Since liquidity runoff and inflow assumptions are held constant across scenarios, liquidity metrics do not vary by rate scenario. This is intended to illustrate model structure rather than dynamic funding stress behavior.
